dungeon_mind/__init__.py
dungeon_mind/llm/__init__.py
dungeon_mind/llm/game_manager.py
dungeon_mind-0.1.0.dist-info/METADATA
dungeon_mind-0.1.0.dist-info/WHEEL
dungeon_mind-0.1.0.dist-info/RECORD
