Metadata-Version: 2.1
Name: dungeon-mind
Version: 0.1.0
Summary: AI-powered game management system that enhances tabletop role-playing experiences
Author: sebastian-hsu
Author-email: sebastian.hsu@gmail.com
Requires-Python: >=3.11,<3.13
Classifier: Programming Language :: Python :: 3
Classifier: Programming Language :: Python :: 3.11
Classifier: Programming Language :: Python :: 3.12
Requires-Dist: game-realm-keeper (>=0.1.0,<0.2.0)
Requires-Dist: pyautogen (>=0.2.32,<0.3.0)
